monsterurl/__init__.py
monsterurl/assets/adjectives
monsterurl/assets/monsters
monsterurl-0.2.dist-info/DESCRIPTION.rst
monsterurl-0.2.dist-info/METADATA
monsterurl-0.2.dist-info/RECORD
monsterurl-0.2.dist-info/WHEEL
monsterurl-0.2.dist-info/metadata.json
monsterurl-0.2.dist-info/top_level.txt
