Metadata-Version: 2.0
Name: monsterurl
Version: 0.2
Summary: A generator of monstruous url names
Home-page: http://github.com/jantoniomartin/monsterurl
Author: Jose Antonio Martin
Author-email: jantonio.martin@gmail.com
License: License :: OSI Approved :: GNU General Public License v2 (GPLv2)
Platform: UNKNOWN
